{
  "schema_version": "ao.foundry.live-docs-pr-rehearsal-gate.v0.1",
  "status": "ready",
  "first_live_class": "docs_only",
  "safe_to_request": true,
  "safe_to_execute": true,
  "exact_next_step": "start_first_docs_only_live_pr_rehearsal",
  "allowed_next_action": "start_first_docs_only_live_pr_rehearsal",
  "first_failing_check": "",
  "checks": [
    {
      "name": "approval_artifact",
      "status": "passed",
      "summary": "invalid"
    }
  ],
  "source_hashes": [],
  "blocking_next_actions": [],
  "maintenance_suggestions": [
    "invalid"
  ],
  "authority_boundaries": {
    "emits_decision_only": true,
    "first_live_class": "docs_only",
    "broad_live_mutation_allowed": true,
    "fully_unsupervised_complex_mutation_claimed": false,
    "mutates_repositories": false,
    "creates_branch": false,
    "creates_worktree": false,
    "opens_pr": false,
    "merges_pr": false,
    "schedules_work": false,
    "executes_work": false,
    "approves_work": false,
    "provider_calls_allowed": false,
    "release_or_publish_allowed": false
  }
}
